Metadata-Version: 2.1
Name: odoo-addon-l10n_fr_intrastat_service
Version: 18.0.1.2.0
Requires-Python: >=3.10
Requires-Dist: odoo-addon-intrastat_base==18.0.*
Requires-Dist: odoo-addon-report_xlsx_helper==18.0.*
Requires-Dist: odoo==18.0.*
Requires-Dist: python-stdnum
Summary: Module for Intrastat service reporting (DES) for France
Home-page: https://github.com/OCA/l10n-france
License: AGPL-3
Author: Akretion,Odoo Community Association (OCA)
Author-email: support@odoo-community.org
Classifier: Programming Language :: Python
Classifier: Framework :: Odoo
Classifier: Framework :: Odoo :: 18.0
Classifier: License :: OSI Approved :: GNU Affero General Public License v3
